plone.app.viewletmanager-4.0.5-py3.13-nspkg.pth
plone/app/viewletmanager/__init__.py
plone/app/viewletmanager/configure.zcml
plone/app/viewletmanager/interfaces.py
plone/app/viewletmanager/manage-viewletmanager.pt
plone/app/viewletmanager/manage-viewlets.pt
plone/app/viewletmanager/manager.py
plone/app/viewletmanager/storage.py
plone/app/viewletmanager/testing.py
plone/app/viewletmanager/exportimport/__init__.py
plone/app/viewletmanager/exportimport/configure.zcml
plone/app/viewletmanager/exportimport/storage.py
plone/app/viewletmanager/tests/__init__.py
plone/app/viewletmanager/tests/manager.rst
plone/app/viewletmanager/tests/storage.rst
plone/app/viewletmanager/tests/test_docs.py
plone/app/viewletmanager/tests/test_exportimport.py
plone_app_viewletmanager-4.0.5.dist-info/METADATA
plone_app_viewletmanager-4.0.5.dist-info/WHEEL
plone_app_viewletmanager-4.0.5.dist-info/namespace_packages.txt
plone_app_viewletmanager-4.0.5.dist-info/top_level.txt
plone_app_viewletmanager-4.0.5.dist-info/RECORD
